mvi.py
mvi-2.0.dist-info/entry_points.txt
mvi-2.0.dist-info/LICENSE
mvi-2.0.dist-info/WHEEL
mvi-2.0.dist-info/METADATA
mvi-2.0.dist-info/RECORD
