Metadata-Version: 2.1
Name: mvi
Version: 2.0
Summary: Move Interactively
Author-email: Gertjan van Zwieten <git@gjvz.nl>
Requires-Python: >=3.8
Classifier: License :: OSI Approved :: MIT License
